pandarus_remote/__init__.py
pandarus_remote/app.py
pandarus_remote/bin.py
pandarus_remote/db.py
pandarus_remote/filesystem.py
pandarus_remote/tasks.py
pandarus_remote/utils.py
pandarus_remote-1.0.dist-info/DESCRIPTION.rst
pandarus_remote-1.0.dist-info/METADATA
pandarus_remote-1.0.dist-info/RECORD
pandarus_remote-1.0.dist-info/WHEEL
pandarus_remote-1.0.dist-info/entry_points.txt
pandarus_remote-1.0.dist-info/metadata.json
pandarus_remote-1.0.dist-info/top_level.txt
