Metadata-Version: 2.0
Name: pandarus-remote
Version: 1.0
Summary: UNKNOWN
Home-page: https://github.com/cmutel/pandarus_remote
Author: Chris Mutel
Author-email: cmutel@gmail.com
License: Copyright (c) 2016, Chris Mutel and Paul Scherrer Institut
Requires-Dist: appdirs
Requires-Dist: docopt
Requires-Dist: fiona
Requires-Dist: flask
Requires-Dist: pandarus (>=1.0)
Requires-Dist: peewee
Requires-Dist: rasterio
Requires-Dist: redis
Requires-Dist: requests
Requires-Dist: rq
